wagtail_color_panel/__init__.py
wagtail_color_panel/blocks.py
wagtail_color_panel/edit_handlers.py
wagtail_color_panel/fields.py
wagtail_color_panel/validators.py
wagtail_color_panel/widgets.py
wagtail_color_panel/migrations/__init__.py
wagtail_color_panel/static/wagtail_color_panel/css/color-input-widget.css
wagtail_color_panel/static/wagtail_color_panel/js/color-input-controller.js
wagtail_color_panel/static/wagtail_color_panel/js/color-input-widget-telepath.js
wagtail_color_panel/static/wagtail_color_panel/js/color-input-widget.js
wagtail_color_panel/templates/wagtail_color_panel/widgets/color-input-widget.html
wagtail_color_panel-1.6.0.dist-info/LICENSE
wagtail_color_panel-1.6.0.dist-info/METADATA
wagtail_color_panel-1.6.0.dist-info/WHEEL
wagtail_color_panel-1.6.0.dist-info/top_level.txt
wagtail_color_panel-1.6.0.dist-info/RECORD
